data_pipeline/__init__.py
data_pipeline/data_visualization/README.md
data_pipeline/data_visualization/__init__.py
data_pipeline/data_visualization/eda.ipynb
data_pipeline/data_visualization/scripts/__init__.py
data_pipeline/data_visualization/scripts/load_dfs.py
data_pipeline/data_visualization/scripts/plot_allelic_imbalance.py
data_pipeline/data_visualization/scripts/plot_caqtl.py
data_pipeline/data_visualization/scripts/plot_tn5.py
data_pipeline/scripts/__init__.py
data_pipeline/scripts/cli.py
data_pipeline/scripts/data_pipeline.py
data_pipeline/scripts/data_processor.py
data_pipeline/scripts/file_handler.py
data_pipeline/scripts/update_config.py
data_pipeline/utils/__init__.py
data_pipeline/utils/config_utils.py
data_pipeline/utils/constants.py
data_pipeline_ml_caqtl_visualization-0.2.1.dist-info/METADATA
data_pipeline_ml_caqtl_visualization-0.2.1.dist-info/WHEEL
data_pipeline_ml_caqtl_visualization-0.2.1.dist-info/entry_points.txt
data_pipeline_ml_caqtl_visualization-0.2.1.dist-info/RECORD
