Metadata-Version: 2.1
Name: data-pipeline-ml-caqtl-visualization
Version: 0.2.1
Summary: ML visualization pipeline for caQTL evaluation
Home-page: https://github.com/mcvickerlab/CaVarCNN/blob/master
License: MIT
Keywords: machine-learning,visualization,caQTL,PyTorch
Author: Jaureguy760
Author-email: jeffpjaureguy@gmail.com
Requires-Python: >=3.10,<3.13
Classifier: License :: OSI Approved :: MIT License
Classifier: Operating System :: OS Independent
Classifier: Programming Language :: Python :: 3
Classifier: Programming Language :: Python :: 3.10
Classifier: Programming Language :: Python :: 3.11
Classifier: Programming Language :: Python :: 3.12
Requires-Dist: click
Requires-Dist: h5py
Requires-Dist: matplotlib
Requires-Dist: numpy
Requires-Dist: pandas
Requires-Dist: polars
Requires-Dist: scipy
Requires-Dist: statsmodels
Project-URL: Repository, https://github.com/mcvickerlab/CaVarCNN/blob/master
